vex_ast/README.md
vex_ast/READMEAPI.md
vex_ast/__init__.py
vex_ast/ast/README.md
vex_ast/ast/__init__.py
vex_ast/ast/core.py
vex_ast/ast/expressions.py
vex_ast/ast/interfaces.py
vex_ast/ast/literals.py
vex_ast/ast/navigator.py
vex_ast/ast/operators.py
vex_ast/ast/statements.py
vex_ast/ast/validators.py
vex_ast/ast/vex_nodes.py
vex_ast/parser/README.md
vex_ast/parser/__init__.py
vex_ast/parser/factory.py
vex_ast/parser/interfaces.py
vex_ast/parser/python_parser.py
vex_ast/parser/strategies.py
vex_ast/registry/README.md
vex_ast/registry/__init__.py
vex_ast/registry/api.py
vex_ast/registry/categories.py
vex_ast/registry/language_map.py
vex_ast/registry/registry.py
vex_ast/registry/signature.py
vex_ast/registry/simulation_behavior.py
vex_ast/registry/validation.py
vex_ast/registry/functions/__init__.py
vex_ast/registry/functions/constructors.py
vex_ast/registry/functions/display.py
vex_ast/registry/functions/drivetrain.py
vex_ast/registry/functions/initialize.py
vex_ast/registry/functions/motor.py
vex_ast/registry/functions/sensors.py
vex_ast/registry/functions/timing.py
vex_ast/serialization/__init__.py
vex_ast/serialization/json_deserializer.py
vex_ast/serialization/json_serializer.py
vex_ast/serialization/schema.py
vex_ast/types/README.md
vex_ast/types/__init__.py
vex_ast/types/base.py
vex_ast/types/enums.py
vex_ast/types/objects.py
vex_ast/types/primitives.py
vex_ast/types/type_checker.py
vex_ast/utils/README.md
vex_ast/utils/__init__.py
vex_ast/utils/errors.py
vex_ast/utils/source_location.py
vex_ast/utils/type_definitions.py
vex_ast/visitors/README.md
vex_ast/visitors/__init__.py
vex_ast/visitors/analyzer.py
vex_ast/visitors/base.py
vex_ast/visitors/printer.py
vex_ast/visitors/transformer.py
vex_ast-0.2.7.dist-info/licenses/LICENSE
vex_ast-0.2.7.dist-info/METADATA
vex_ast-0.2.7.dist-info/WHEEL
vex_ast-0.2.7.dist-info/top_level.txt
vex_ast-0.2.7.dist-info/RECORD
