Metadata-Version: 2.4
Name: vex_ast
Version: 0.2.7
Summary: A Python package for generating Abstract Syntax Trees for VEX V5 code.
Home-page: https://github.com/heartx2/vex_ast
Author: Chaze
Author-email: Chaze <chazelexander@gmail.com>
License: HX2's Vex AST © 2025 by charkwayteowy is licensed under CC BY-NC 4.0
Project-URL: Repository, https://github.com/heartx2/vex_ast
Classifier: Development Status :: 3 - Alpha
Classifier: Intended Audience :: Developers
Classifier: Programming Language :: Python :: 3
Classifier: Programming Language :: Python :: 3.8
Classifier: Programming Language :: Python :: 3.9
Classifier: Programming Language :: Python :: 3.10
Classifier: Programming Language :: Python :: 3.11
Classifier: Topic :: Software Development :: Compilers
Classifier: Topic :: Software Development :: Libraries :: Python Modules
Requires-Python: >=3.8
License-File: LICENSE
Dynamic: author
Dynamic: home-page
Dynamic: license-file
Dynamic: requires-python
